read_protobuf.py
read_protobuf-0.2.0.dist-info/LICENSE
read_protobuf-0.2.0.dist-info/METADATA
read_protobuf-0.2.0.dist-info/WHEEL
read_protobuf-0.2.0.dist-info/top_level.txt
read_protobuf-0.2.0.dist-info/RECORD
