Metadata-Version: 2.1
Name: read-protobuf
Version: 0.2.0
Summary: Small library to read serialized protobuf(s) directly into Pandas DataFrame
Author: Marc Shapiro
License: MIT
Project-URL: Issues, https://github.com/mlshapiro/read-protobuf/issues
Project-URL: Repository, https://github.com/mlshapiro/read-protobuf.git
Keywords: pandas,protobuf
Requires-Python: >=3.7
License-File: LICENSE
Requires-Dist: pandas (>=2.0.1)
Requires-Dist: protobuf (>=4.21.1)
Provides-Extra: dev
Requires-Dist: black (>=22) ; extra == 'dev'
Requires-Dist: black[jupyter] ; extra == 'dev'
Requires-Dist: build ; extra == 'dev'
Requires-Dist: ipdb (>=0.13) ; extra == 'dev'
Requires-Dist: isort (>=5.4) ; extra == 'dev'
Requires-Dist: jupyterlab (>=4.0) ; extra == 'dev'
Requires-Dist: pytest (>=6.1) ; extra == 'dev'
Requires-Dist: pytest-cov (>=2.11) ; extra == 'dev'
Requires-Dist: ruff (>=0.0.259) ; extra == 'dev'
Requires-Dist: twine ; extra == 'dev'
